{
  "name": "Accordion",
  "category": "Skapa-components",
  "source": "Screenshot from skapa.ikea.net",
  "extractedAt": "2025-11-02T08:45:28.036Z",
  "extractionMethod": "tesseract-ocr",
  "description": "OCR extracted component specification (heuristic)",
  "variants": [
    {
      "name": "info"
    }
  ],
  "states": [
    {
      "name": "loading"
    }
  ],
  "content": {
    "rawText": "OD) Skapa ¢ Q Search\nAbout Skapa v\nDesigning v\nLast updated: 2025-05-14\nDeveloping v °\nFoundations v Accordion\nComponents A\nA list of headers that hide or reveal additional content when selected.\nOverview\nComponent availability\nAccordion e”\nApp Bar\nAspect Ratio Box\nAvatar\nBadge\nBanner\nBroken Image\nButton\nCard\nCarousel\nCheckbox\nChoice\nCombobox\nCommercial Message Available for\nCompact Card { Figma Open\nCopyright Notice\nDivider & React Open\nDual Button\nCo) Web Component Open\nEndorsement Label\nExpander\nP Android Open\nExpanding Button\ntA\nHelper Text S ios Open\nHyperlink\nIcon Button\nIndex Anatomy\nIcon Pill\nVariants\nImage\nBehaviours\nInline Message\nUsage\nInput Field\nMotion\nJumbo Button\nInternationalisation\nList\nKeyboard Interactions\nList View Item\nListbox\nLoading A\nMember Card nato y\nMenu Item\nModal containers\nPayment Logo\nPill\nPrice\nPrice Module\nProduct Identifier\nProduct type\nProgress Indicator Table he Accordion Header\nPrompt\nQuantity Stepper Product details ~\nRadio Button\ni This clothes bag has 2 compartments - one with\nRating mesh fabric for clean clothes and one with a zipper\nwhere you can hide dirty clothes.\nSearch y y\nSegmented Control Fits perfectly in DROMSACK and VARLDENS\nbackpacks and weekend bags, and in STUK box\nSelect (Native) with compartments (34x51x10 cm).\nSheet\nShoppable Image Title —— Product size\nv —— Affordance\n500x500cm\nSimple Video WIP | (Pre\nSkeleton |\nslider Caption\nStatus\nSwitch\nTable\nTabs\nTag\nText\nfetes Variants\nText Overlay Card\nTheatre .\nSizes\nToast i i . . i . . i\nAccordion is available in three different sizes. The height will\nToggle expand if the text size is increased. Use medium and large list\nTitle v items for double lines of text.\nTooltip\nVideo\nSmall\nAndroid v\nios v\nVue Vv\nWeb Components v Title v\nPatterns v\nSubsystems v RAEI\nSupport v\nTitle v\nLarge\nRegular and subtle title\nThe title row in Accordion supports both regular and emphasised\ntext.\nTitle v\nRegular\nTitle v\nSubtle\nSingle line or double line labels\nThe small Accordion only supports a single line of text, while the\nmedium and large versions support double lines.\nTitle v\nSingle Line\nTitle\nv\nCaption\nDouble Line\nEdge to edge or inset\nAccordion can span the entire width of a viewport, such as on\nmobile web and small screens, or they can be inset and nested\nitle v within a layout. The dividers just span the width of the\ncomponent, leaving the container to provide its own padding.\nAccordion on mobile native always has a fixed horizontal\nEdge to edge padding.\n- v\nInset\nBehaviours\nCollapsed state\nThe icon arrow points downwards when the Accordion is\ncollapsed.\nTrack my order v\nCustomer services v\nFAQs v\nReturn policy v\nPayment v\nExpanded state\nThe icon arrow points upwards when the Accordion is expanded.\nTrack my order v\nCustomer services A\nPlanners v\nLong header\nHeaders with more than two lines of text will automatically\nincrease the height of the Accordion. The text and icon should\nalways be vertically centered.\nPayment v\nWhen am | entitled to claim a VAT\nrefund and what do | need to do to v\nobtain one?\nSponsorship and Charity Requests v\nLong caption\nCaptions with more than one line of text will automatically\nincrease the height of the Accordion. The text and icon should\nalways be vertically centered.\nOnline planning appointment “\nGet help from home\nDelivery Information\nAll you need regarding delivery from your v\nlocal IKEA Store\nTaskRabbit “\nAn Assembly service for you\nBreaking information into smaller pieces\nUse Accordions to create an overview by gathering related information.\nHelp IKEA Family\nTrack my order v Welcome to IKEA Family v\nCustomer services v About v\nPlanners v Offers v\nFAQs v Benefits v\nL_________________________________________________________________________________________________________________J\n()\nStick to a single header variant\nScanning an Accordion is easier when the design pattern is consistent.\nTrack my order\nTrack my order v y v\nHave control of your order\nCustomer services v Customer services v\nPlanners\nPlanners v v\nGet help from home\nFAQs v FAQs v\nL________________________________________________________________________________ ____________J\n(] A consistent Accordion composition that's easier to scan. (1) An inconsistent Accordion composition that's more challenging to scan.\nTreat headlines correctly\nThe Accordion is designed to help the user to get a quick and clear overview of\ninformation. Treat headlines as proper headlines to keep the character count low.\nWhat payment methods do you accept? v What payment methods do you accept? v\nWhen am I entitled to claim a VAT refund “ When am I entitled to claim a VAT refund\nand what do | need to do to obtain one? on my credit card and what do | need to\ndo to obtain one? v\nTap me for more information\nWhat should I do if my card is declined? v\nWhat should I do if my card is declined? v\nIKEA Home Card v\n.__________________________________________________________________________/ ed ele —— ——\n(] An Accordion with shorter headlines that are easier to read. (1) An Accordion with longer and more varying headlines that are more difficult to\nread.\nMotion\nExpand and collapse\nWhen the Accordion gets activated the bottom divider of the\nselected Accordion expands and pushes down all the content\nplaced underneath it. Meanwhile, the content inside of the\nselected Accordion gets revealed.\nTrack my order v\nSee motion: Easy ease\nCustomer services v\nFAQs v\nReturn policy v\nPayment v\nContent reveal\nElements inside of the Accordion are revealed and hidden using a\nfade-in and a fade-out sequence.\nSee motion: Still fade Easy ease\nAffordance activation\nThe affordance icon is rotating 180° degrees to point upwards\nwhen the Accordion is being expanded.\nSee motion: Easy ease\nInternationalisation\nRTL languages\nAccordions will horizontally flip their content and place icon\n. arrows to the left and headlines to the right.\nv zwb Maalle\nVv Moslalai\n< cle 5 < .\nv Blwidd MLolicd\nKeyboard Interactions\nKey Description\nTab / Arrow Down Jumps to the next Accordion headline.\nShift + Tab / Arrow Up Jumps to the previous Accordion headline.\nEnter / Space Opens and closes the Accordion when it's in focus.\nHome Jumps to first available item.\nEnd Jumps to last available item.\nUp next\nApp Bar >\nXx\n[*]\n[1]\na\nb=\n7}\n1}\n[* 9\nOD © Inter IKEA Systems B.V 1999-2025\n",
    "lines": [
      "OD) Skapa ¢ Q Search",
      "About Skapa v",
      "Designing v",
      "Last updated: 2025-05-14",
      "Developing v °",
      "Foundations v Accordion",
      "Components A",
      "A list of headers that hide or reveal additional content when selected.",
      "Overview",
      "Component availability",
      "Accordion e”",
      "App Bar",
      "Aspect Ratio Box",
      "Avatar",
      "Badge",
      "Banner",
      "Broken Image",
      "Button",
      "Card",
      "Carousel",
      "Checkbox",
      "Choice",
      "Combobox",
      "Commercial Message Available for",
      "Compact Card { Figma Open",
      "Copyright Notice",
      "Divider & React Open",
      "Dual Button",
      "Co) Web Component Open",
      "Endorsement Label",
      "Expander",
      "P Android Open",
      "Expanding Button",
      "tA",
      "Helper Text S ios Open",
      "Hyperlink",
      "Icon Button",
      "Index Anatomy",
      "Icon Pill",
      "Variants",
      "Image",
      "Behaviours",
      "Inline Message",
      "Usage",
      "Input Field",
      "Motion",
      "Jumbo Button",
      "Internationalisation",
      "List",
      "Keyboard Interactions",
      "List View Item",
      "Listbox",
      "Loading A",
      "Member Card nato y",
      "Menu Item",
      "Modal containers",
      "Payment Logo",
      "Pill",
      "Price",
      "Price Module",
      "Product Identifier",
      "Product type",
      "Progress Indicator Table he Accordion Header",
      "Prompt",
      "Quantity Stepper Product details ~",
      "Radio Button",
      "i This clothes bag has 2 compartments - one with",
      "Rating mesh fabric for clean clothes and one with a zipper",
      "where you can hide dirty clothes.",
      "Search y y",
      "Segmented Control Fits perfectly in DROMSACK and VARLDENS",
      "backpacks and weekend bags, and in STUK box",
      "Select (Native) with compartments (34x51x10 cm).",
      "Sheet",
      "Shoppable Image Title —— Product size",
      "v —— Affordance",
      "500x500cm",
      "Simple Video WIP | (Pre",
      "Skeleton |",
      "slider Caption",
      "Status",
      "Switch",
      "Table",
      "Tabs",
      "Tag",
      "Text",
      "fetes Variants",
      "Text Overlay Card",
      "Theatre .",
      "Sizes",
      "Toast i i . . i . . i",
      "Accordion is available in three different sizes. The height will",
      "Toggle expand if the text size is increased. Use medium and large list",
      "Title v items for double lines of text.",
      "Tooltip",
      "Video",
      "Small",
      "Android v",
      "ios v",
      "Vue Vv",
      "Web Components v Title v",
      "Patterns v",
      "Subsystems v RAEI",
      "Support v",
      "Title v",
      "Large",
      "Regular and subtle title",
      "The title row in Accordion supports both regular and emphasised",
      "text.",
      "Title v",
      "Regular",
      "Title v",
      "Subtle",
      "Single line or double line labels",
      "The small Accordion only supports a single line of text, while the",
      "medium and large versions support double lines.",
      "Title v",
      "Single Line",
      "Title",
      "v",
      "Caption",
      "Double Line",
      "Edge to edge or inset",
      "Accordion can span the entire width of a viewport, such as on",
      "mobile web and small screens, or they can be inset and nested",
      "itle v within a layout. The dividers just span the width of the",
      "component, leaving the container to provide its own padding.",
      "Accordion on mobile native always has a fixed horizontal",
      "Edge to edge padding.",
      "- v",
      "Inset",
      "Behaviours",
      "Collapsed state",
      "The icon arrow points downwards when the Accordion is",
      "collapsed.",
      "Track my order v",
      "Customer services v",
      "FAQs v",
      "Return policy v",
      "Payment v",
      "Expanded state",
      "The icon arrow points upwards when the Accordion is expanded.",
      "Track my order v",
      "Customer services A",
      "Planners v",
      "Long header",
      "Headers with more than two lines of text will automatically",
      "increase the height of the Accordion. The text and icon should",
      "always be vertically centered.",
      "Payment v",
      "When am | entitled to claim a VAT",
      "refund and what do | need to do to v",
      "obtain one?",
      "Sponsorship and Charity Requests v",
      "Long caption",
      "Captions with more than one line of text will automatically",
      "increase the height of the Accordion. The text and icon should",
      "always be vertically centered.",
      "Online planning appointment “",
      "Get help from home",
      "Delivery Information",
      "All you need regarding delivery from your v",
      "local IKEA Store",
      "TaskRabbit “",
      "An Assembly service for you",
      "Breaking information into smaller pieces",
      "Use Accordions to create an overview by gathering related information.",
      "Help IKEA Family",
      "Track my order v Welcome to IKEA Family v",
      "Customer services v About v",
      "Planners v Offers v",
      "FAQs v Benefits v",
      "L_________________________________________________________________________________________________________________J",
      "()",
      "Stick to a single header variant",
      "Scanning an Accordion is easier when the design pattern is consistent.",
      "Track my order",
      "Track my order v y v",
      "Have control of your order",
      "Customer services v Customer services v",
      "Planners",
      "Planners v v",
      "Get help from home",
      "FAQs v FAQs v",
      "L________________________________________________________________________________ ____________J",
      "(] A consistent Accordion composition that's easier to scan. (1) An inconsistent Accordion composition that's more challenging to scan.",
      "Treat headlines correctly",
      "The Accordion is designed to help the user to get a quick and clear overview of",
      "information. Treat headlines as proper headlines to keep the character count low.",
      "What payment methods do you accept? v What payment methods do you accept? v",
      "When am I entitled to claim a VAT refund “ When am I entitled to claim a VAT refund",
      "and what do | need to do to obtain one? on my credit card and what do | need to",
      "do to obtain one? v",
      "Tap me for more information",
      "What should I do if my card is declined? v",
      "What should I do if my card is declined? v",
      "IKEA Home Card v",
      ".__________________________________________________________________________/ ed ele —— ——",
      "(] An Accordion with shorter headlines that are easier to read. (1) An Accordion with longer and more varying headlines that are more difficult to",
      "read.",
      "Motion",
      "Expand and collapse",
      "When the Accordion gets activated the bottom divider of the",
      "selected Accordion expands and pushes down all the content",
      "placed underneath it. Meanwhile, the content inside of the",
      "selected Accordion gets revealed.",
      "Track my order v",
      "See motion: Easy ease",
      "Customer services v",
      "FAQs v",
      "Return policy v",
      "Payment v",
      "Content reveal",
      "Elements inside of the Accordion are revealed and hidden using a",
      "fade-in and a fade-out sequence.",
      "See motion: Still fade Easy ease",
      "Affordance activation",
      "The affordance icon is rotating 180° degrees to point upwards",
      "when the Accordion is being expanded.",
      "See motion: Easy ease",
      "Internationalisation",
      "RTL languages",
      "Accordions will horizontally flip their content and place icon",
      ". arrows to the left and headlines to the right.",
      "v zwb Maalle",
      "Vv Moslalai",
      "< cle 5 < .",
      "v Blwidd MLolicd",
      "Keyboard Interactions",
      "Key Description",
      "Tab / Arrow Down Jumps to the next Accordion headline.",
      "Shift + Tab / Arrow Up Jumps to the previous Accordion headline.",
      "Enter / Space Opens and closes the Accordion when it's in focus.",
      "Home Jumps to first available item.",
      "End Jumps to last available item.",
      "Up next",
      "App Bar >",
      "Xx",
      "[*]",
      "[1]",
      "a",
      "b=",
      "7}",
      "1}",
      "[* 9",
      "OD © Inter IKEA Systems B.V 1999-2025"
    ]
  }
}
