{
  "name": "Carousel",
  "category": "Skapa-components",
  "source": "Screenshot from skapa.ikea.net",
  "extractedAt": "2025-11-02T08:48:46.750Z",
  "extractionMethod": "tesseract-ocr",
  "description": "OCR extracted component specification (heuristic)",
  "variants": [],
  "states": [
    {
      "name": "default"
    },
    {
      "name": "hover"
    },
    {
      "name": "disabled"
    },
    {
      "name": "loading"
    }
  ],
  "content": {
    "rawText": "OD) Skapa ¢ Q Search\nAbout Skapa v\nDesigning v\nLast updated: 2025-05-14\nDeveloping v\nFoundations v Carousel\nComponents A\nA container used to horizontally slide or cycle through content placed\nOverview FE .\ninside of it.\nComponent availability\nAccordion\n+\nApp Bar\nAspect Ratio Box\nAvatar\nBadge\nBanner\nBroken Image\nButton\nCard\nCarousel\nCheckbox\nChoice\nCombobox\nCommercial Message\nAvailable for\nCompact Card\nCopyright Notice { Figma Open\nDivider\n& React Open\nDual Button\nEndorsement Label\n\\ 4 Vue (Overflow Carousel only) Open\nExpander\nExpanding Button © Web Components Open\nHelper Text\n) 4m, Android Open\nHyperlink\nIcon Button ’\nS ios Open\nIcon Pill\nImage\nAnatom\nInline Message Index Y\nInput Field Variants\nJumbo Button Behaviours\nList Usage\nList View Item Motion\nListbox Ul Carousel\nLoading Keyboard interactions\nMember Card\nMenu Item\nModal containers Anatomy\nPayment Logo\nPill\nPrice\nPrice Module Content frame Overflow\nProduct Identifier\nProgress Indicator\nPrompt\nQuantity Stepper\nContent ————— [>]\nRadio Button\nRating\nSearch\nSegmented Control EE\nSelect (Native)\nHandle Track Scrollbar Slider controls\nSheet\nShoppable Image\nSimple Video WIP | (Pre\nSkeleton\nSlider\neo\nStatus Variants\nSwitch\nTable Free-scrolling\nTabs Free-scrolling Carousels allow the user to move the content like a regular scroll area,\nfollowing the precise control of trackpad, mouse wheel or scrollbar inputs. This is the\nTag default scrolling behaviour.\nText\nText Area\nText Overlay Card\nTheatre\nToast - -\n} [ xX el\niT | TR Sing AR 1 Hy, CE f \\ A\nToggle i - ax J | Lm I “HE hy, fl : [ Fl rin oY ay\nF=—1 rt = - Bo 4 L Sy \\ | ea Rl HH : Be | Je ! hn\n. al | LE I Yow] i w= ~ - RPT : Cag\nTooltip A = | teh 1 =. AKER [Puja da» a =\nVideo ow oe ne - [\nHome visit: a big family in a The importance of ergonomic A creative space for bosses, Home visit: a garage turned First the pr\nsmall house office furniture both big and small creative workspace pizzas.\nAndroid v\nios Vv > > > > >\nVue v\nWeb Components v\nPatterns v\nSubsystems v\nSupport v\nSlideshow\nSlideshow Carousels rotate the content to show each of its nested content one at a\ntime. While a user can still scroll with all available inputs, the Carousel will always snap\nand centre to the following or previous frame.\nImages retain their natural size but are scaled to fit within a fixed height of the\nCarousel.\nBehaviours\nCarousels are used to place content inside of its content frame. Users can navigate\nthem by using the scrollbar, slider controls, native scrolling or gestures.\nHandle\nThe position and width of the handle is a representation of the content currently visible\nin the content frame, relative to the total width of all content.\nThe handle is a draggable element on a pointer device, allowing users to pick it up and\nmove it with their cursor. Clicking or tapping anywhere on the scrollbar track will\nattempt to centre the handle on that point, scrolling the contents as it moves to its new\nposition.\n—_—lr\nSlider controls\nSlider controls will attempt to align the content to the nearest overflow item in the\ndirection of the control. Slider controls are disabled on touch devices.\n>\n\\s\nNearest overflow item displayed in pink.\nClicking aligns the nearest overflow item to the opposite edge of the scroll area.\nControl alignment is adjusted in small viewports to allow for the touch area to remain inside the page container.\nNative scrolling\nCarousels allow content scrolling via trackpad, mouse wheel or swiping gestures.\nCarousels without overflow\nSlider controls and scrollbars are hidden when there is no overflow.\nEmbrace visual overflow\nRevealing overflow provides gives users a useful hint that there's more content for them\nto see.\nOverflow runs off the edge of the screen on a large breakpoint.\nIn some cases, revealing overflow interferes with neighboring content. If so, overflow\nshould be hidden.\nCarousel with neighboring fixed elements.\nContent length\nWhen possible, avoid making the Carousel too long as this makes it difficult for the user\nto scroll through. Try to keep Carousels to five frames or less. The number of frames\ncan render differently depending on the Carousel's viewport. At minimum, ensure there\nis 1 frame in full view.\nFrame 1 Frame 2 Frame 3 Frame 4 Frame 5\nMotion\nSlider controls\nCarousel controls move content by sliding it horizontally to its new position.\n» Use Easy Ease\n+ Use a Standard Duration\nScrollbar\nThe track expands on hover, and the handle within the track expands additionally on\npress or mouse down. The items expand from the center.\n» Use Easy Ease\n+ Use a Standard Duration\nUl Carousels are a special, more minimal version of a Carousel that are used to slide\nhorizontally flowing Ul (e.g. tab bars and pill groups) as opposed to content.\nThese Carousels use the same Carousel code and logic, but remove features like the\nscrollbar and keyboard focusable ‘skip content’ buttons. They also have a different set of\ninteraction behaviours, as noted below.\nUl Carousels are not a typical component. They're a design pattern that is applied to\ngroups of Ul elements.\nPointer devices\nOverflow controls are always present on pointer devices. A user can navigate the\nCarousel by using the slider controls and native scrolling.\nBedroom Living room Kitchen Dining Baby & children Bathroom LJ\nPills can be scrolled via clicking the overflow controls or native scrolling.\nTouch devices\nThe presence of overflow controls is dependent on the user's first interaction with a\n",
    "lines": [
      "OD) Skapa ¢ Q Search",
      "About Skapa v",
      "Designing v",
      "Last updated: 2025-05-14",
      "Developing v",
      "Foundations v Carousel",
      "Components A",
      "A container used to horizontally slide or cycle through content placed",
      "Overview FE .",
      "inside of it.",
      "Component availability",
      "Accordion",
      "+",
      "App Bar",
      "Aspect Ratio Box",
      "Avatar",
      "Badge",
      "Banner",
      "Broken Image",
      "Button",
      "Card",
      "Carousel",
      "Checkbox",
      "Choice",
      "Combobox",
      "Commercial Message",
      "Available for",
      "Compact Card",
      "Copyright Notice { Figma Open",
      "Divider",
      "& React Open",
      "Dual Button",
      "Endorsement Label",
      "\\ 4 Vue (Overflow Carousel only) Open",
      "Expander",
      "Expanding Button © Web Components Open",
      "Helper Text",
      ") 4m, Android Open",
      "Hyperlink",
      "Icon Button ’",
      "S ios Open",
      "Icon Pill",
      "Image",
      "Anatom",
      "Inline Message Index Y",
      "Input Field Variants",
      "Jumbo Button Behaviours",
      "List Usage",
      "List View Item Motion",
      "Listbox Ul Carousel",
      "Loading Keyboard interactions",
      "Member Card",
      "Menu Item",
      "Modal containers Anatomy",
      "Payment Logo",
      "Pill",
      "Price",
      "Price Module Content frame Overflow",
      "Product Identifier",
      "Progress Indicator",
      "Prompt",
      "Quantity Stepper",
      "Content ————— [>]",
      "Radio Button",
      "Rating",
      "Search",
      "Segmented Control EE",
      "Select (Native)",
      "Handle Track Scrollbar Slider controls",
      "Sheet",
      "Shoppable Image",
      "Simple Video WIP | (Pre",
      "Skeleton",
      "Slider",
      "eo",
      "Status Variants",
      "Switch",
      "Table Free-scrolling",
      "Tabs Free-scrolling Carousels allow the user to move the content like a regular scroll area,",
      "following the precise control of trackpad, mouse wheel or scrollbar inputs. This is the",
      "Tag default scrolling behaviour.",
      "Text",
      "Text Area",
      "Text Overlay Card",
      "Theatre",
      "Toast - -",
      "} [ xX el",
      "iT | TR Sing AR 1 Hy, CE f \\ A",
      "Toggle i - ax J | Lm I “HE hy, fl : [ Fl rin oY ay",
      "F=—1 rt = - Bo 4 L Sy \\ | ea Rl HH : Be | Je ! hn",
      ". al | LE I Yow] i w= ~ - RPT : Cag",
      "Tooltip A = | teh 1 =. AKER [Puja da» a =",
      "Video ow oe ne - [",
      "Home visit: a big family in a The importance of ergonomic A creative space for bosses, Home visit: a garage turned First the pr",
      "small house office furniture both big and small creative workspace pizzas.",
      "Android v",
      "ios Vv > > > > >",
      "Vue v",
      "Web Components v",
      "Patterns v",
      "Subsystems v",
      "Support v",
      "Slideshow",
      "Slideshow Carousels rotate the content to show each of its nested content one at a",
      "time. While a user can still scroll with all available inputs, the Carousel will always snap",
      "and centre to the following or previous frame.",
      "Images retain their natural size but are scaled to fit within a fixed height of the",
      "Carousel.",
      "Behaviours",
      "Carousels are used to place content inside of its content frame. Users can navigate",
      "them by using the scrollbar, slider controls, native scrolling or gestures.",
      "Handle",
      "The position and width of the handle is a representation of the content currently visible",
      "in the content frame, relative to the total width of all content.",
      "The handle is a draggable element on a pointer device, allowing users to pick it up and",
      "move it with their cursor. Clicking or tapping anywhere on the scrollbar track will",
      "attempt to centre the handle on that point, scrolling the contents as it moves to its new",
      "position.",
      "—_—lr",
      "Slider controls",
      "Slider controls will attempt to align the content to the nearest overflow item in the",
      "direction of the control. Slider controls are disabled on touch devices.",
      ">",
      "\\s",
      "Nearest overflow item displayed in pink.",
      "Clicking aligns the nearest overflow item to the opposite edge of the scroll area.",
      "Control alignment is adjusted in small viewports to allow for the touch area to remain inside the page container.",
      "Native scrolling",
      "Carousels allow content scrolling via trackpad, mouse wheel or swiping gestures.",
      "Carousels without overflow",
      "Slider controls and scrollbars are hidden when there is no overflow.",
      "Embrace visual overflow",
      "Revealing overflow provides gives users a useful hint that there's more content for them",
      "to see.",
      "Overflow runs off the edge of the screen on a large breakpoint.",
      "In some cases, revealing overflow interferes with neighboring content. If so, overflow",
      "should be hidden.",
      "Carousel with neighboring fixed elements.",
      "Content length",
      "When possible, avoid making the Carousel too long as this makes it difficult for the user",
      "to scroll through. Try to keep Carousels to five frames or less. The number of frames",
      "can render differently depending on the Carousel's viewport. At minimum, ensure there",
      "is 1 frame in full view.",
      "Frame 1 Frame 2 Frame 3 Frame 4 Frame 5",
      "Motion",
      "Slider controls",
      "Carousel controls move content by sliding it horizontally to its new position.",
      "» Use Easy Ease",
      "+ Use a Standard Duration",
      "Scrollbar",
      "The track expands on hover, and the handle within the track expands additionally on",
      "press or mouse down. The items expand from the center.",
      "» Use Easy Ease",
      "+ Use a Standard Duration",
      "Ul Carousels are a special, more minimal version of a Carousel that are used to slide",
      "horizontally flowing Ul (e.g. tab bars and pill groups) as opposed to content.",
      "These Carousels use the same Carousel code and logic, but remove features like the",
      "scrollbar and keyboard focusable ‘skip content’ buttons. They also have a different set of",
      "interaction behaviours, as noted below.",
      "Ul Carousels are not a typical component. They're a design pattern that is applied to",
      "groups of Ul elements.",
      "Pointer devices",
      "Overflow controls are always present on pointer devices. A user can navigate the",
      "Carousel by using the slider controls and native scrolling.",
      "Bedroom Living room Kitchen Dining Baby & children Bathroom LJ",
      "Pills can be scrolled via clicking the overflow controls or native scrolling.",
      "Touch devices",
      "The presence of overflow controls is dependent on the user's first interaction with a"
    ]
  }
}
