{
  "name": "Jumbo-Button",
  "category": "Skapa-components",
  "source": "Screenshot from skapa.ikea.net",
  "extractedAt": "2025-11-01T10:24:54.318Z",
  "extractionMethod": "tesseract-ocr",
  "description": "OCR extracted component specification (heuristic)",
  "variants": [
    {
      "name": "primary"
    },
    {
      "name": "secondary"
    },
    {
      "name": "info"
    }
  ],
  "states": [
    {
      "name": "loading"
    }
  ],
  "content": {
    "rawText": "OD) Skapa ¢ Q Search\nAbout Skapa v\nDesigning v\nLast updated: 2025-05-14\nDeveloping v\nontaions Jumbo Button\nComponents A\nUsed to trigger the final action on a linear flow.\nOverview\ncro\n; Addons ~\nComponent availability Emphasised he © ons 5 ®\nAccordion Buttons\nDual Button Button text Label\nApp Bar i J\nExpanding Button Label >]\nAspect Ratio Box IconPill footer False\nIcon Button\nAvatar a\nJumbo Button Clabes False\nBadge Documentation\n[1 Emphasised loading False\nBanner\nFooter variant width behaviour\nBroken Image Pill href\n(converts J\nButton button to\n<a> tag)\nCard Checkbox\nChoice\nCarousel\nCombobox\nCheckbox Input Field\nQuantity Stepper\nChoice }\nCombobox\nCommercial Message Available for\nC t Card .\nompact Car { Figma Open\nCopyright Notice\nDivider & React Open\nDual Button\n\\ 4 Vue Open\nEndorsement Label\nExpander\nP Android Open\nExpanding Button\ntA\nHelper Text S ios Open\nHyperlink\nIcon Button\nIndex Anatomy\nIcon Pill\nVariants\nImage\nBehaviours\nInline Message\nUsage\nInput Field\nInternationalisation\nJumbo Button\nKeyboard interactions\nList\nFurther reading\nList View Item\nListbox\nLoading\nMember Card nato y\nMenu Item\nModal containers\nPayment Logo\nPill Background\nPrice\nPrice Module\nProduct Identifier\nProgress Indicator\nButton label (>)\nPrompt\nQuantity Stepper\nRadio Button\nRating i.\nLabel Trailing Icon\nSearch\nSegmented Control\nSelect (Native)\nSheet\nShoppable Image\nSimple Video WIP | (Pre Va ria nts\nSkeleton\nSlider\nRegular Jumbo Button\nStatus\nRegular variant is used when contained within a grid.\nSwitch\nTable\nButton label >]\nTabs\nTag\nText\nText Area\nText Overlay Card Footer Jumbo Button\nTheatre Footer variant is used to span edge-to-edge at the bottom of a\ncontainer, typically on narrow screens.\nToast\nButton label (> ]\nToggle\nTooltip\nVideo\nAndroid v\nios v\nVue Vv\no\nWeb Components v Behaviou rs\nPatterns v\nSubsystems v Text overflow\nSupport Vv Buttons respect their height. Buttons are able to wrap up to 2\nlines of text before truncating their labels.\nReally really really long (>)\nJumbo Button label trunc...\nJumbo Buttons are used to emphasise the final step of a\nlinear flow, typically at the end of a purchase journey\nIts core objective is to emphasise a critical action that is to be taken next. Consider only\nusing the Jumbo Buttons in the final step of a flow, as its visual prominence will be\nmore useful to convey a critical decision, such as the confirmation of a payment in the\npurchase flow.\nContact information Payment method >\nOrder summary\nBeing consistent across steps helps create a unified linear flow.\nDo not pair Jumbo Buttons with any other secondary\nactions\nGive the user a clear suggestion on how to move forward by presenting only a single\nprimary action on each screen.\nDelivery details > Delivery details >\nContinue shopping\nComplete purchase (> ] Complete purchase (> ]\nL____________________________________________________________________________. _____________J\n(] Present Jumbo Buttons as a stand-alone final action of the screen. (1) Don't pair Jumbo Buttons with secondary actions. Jumbo buttons are only used to\nprogress linear flows.\nRegular Jumbo Button vs. Footer Jumbo Button\nRegular variant is suitable for use on larger screens. They are inset and inline like a\ntypical button. The Footer variant can make the button label and arrow affordance feel\ndistant when stretched too wide. The Footer variant is better suited to small screens or\ncontainers and usually bookends the screen by filling it from edge to edge.\nPayment method >\nComfort configurator\n.________________________________________________________________________________ _________________J\n(] Use Regular Jumbo Button on larger screens. (] Use Footer Jumbo Button on mobile-only designs.\nUse a verb in the label. Be concise.\nButtons perform actions. Use a verb to set the expectation of what action it performs.\nRead more about writing for buttons.\nLet's complete your purchase\nComplete purchase >] i\nP P of the planed kitchen\nL________________________________________________________________________________ _______________J\n(] “Complete purchase” provides clear expectation of this button's action. (1) Avoid use of long labels that read like a sentence. Provide context outside, around\nthe button instead of inside it.\nInternationalisation\nRTL languages\nText and Icon will flip its placement position to the opposite side.\n(<] ues sled Mails\nKeyboard interactions\nKey Description\nSpace / Enter Triggers Button action.\nFurther reading\nDesigning forms >\nUp next\no\nList i\nXx\n[*]\n[1]\na\nb=\n7}\n1}\n[* 9\nOD © Inter IKEA Systems B.V 1999-2025\n",
    "lines": [
      "OD) Skapa ¢ Q Search",
      "About Skapa v",
      "Designing v",
      "Last updated: 2025-05-14",
      "Developing v",
      "ontaions Jumbo Button",
      "Components A",
      "Used to trigger the final action on a linear flow.",
      "Overview",
      "cro",
      "; Addons ~",
      "Component availability Emphasised he © ons 5 ®",
      "Accordion Buttons",
      "Dual Button Button text Label",
      "App Bar i J",
      "Expanding Button Label >]",
      "Aspect Ratio Box IconPill footer False",
      "Icon Button",
      "Avatar a",
      "Jumbo Button Clabes False",
      "Badge Documentation",
      "[1 Emphasised loading False",
      "Banner",
      "Footer variant width behaviour",
      "Broken Image Pill href",
      "(converts J",
      "Button button to",
      "<a> tag)",
      "Card Checkbox",
      "Choice",
      "Carousel",
      "Combobox",
      "Checkbox Input Field",
      "Quantity Stepper",
      "Choice }",
      "Combobox",
      "Commercial Message Available for",
      "C t Card .",
      "ompact Car { Figma Open",
      "Copyright Notice",
      "Divider & React Open",
      "Dual Button",
      "\\ 4 Vue Open",
      "Endorsement Label",
      "Expander",
      "P Android Open",
      "Expanding Button",
      "tA",
      "Helper Text S ios Open",
      "Hyperlink",
      "Icon Button",
      "Index Anatomy",
      "Icon Pill",
      "Variants",
      "Image",
      "Behaviours",
      "Inline Message",
      "Usage",
      "Input Field",
      "Internationalisation",
      "Jumbo Button",
      "Keyboard interactions",
      "List",
      "Further reading",
      "List View Item",
      "Listbox",
      "Loading",
      "Member Card nato y",
      "Menu Item",
      "Modal containers",
      "Payment Logo",
      "Pill Background",
      "Price",
      "Price Module",
      "Product Identifier",
      "Progress Indicator",
      "Button label (>)",
      "Prompt",
      "Quantity Stepper",
      "Radio Button",
      "Rating i.",
      "Label Trailing Icon",
      "Search",
      "Segmented Control",
      "Select (Native)",
      "Sheet",
      "Shoppable Image",
      "Simple Video WIP | (Pre Va ria nts",
      "Skeleton",
      "Slider",
      "Regular Jumbo Button",
      "Status",
      "Regular variant is used when contained within a grid.",
      "Switch",
      "Table",
      "Button label >]",
      "Tabs",
      "Tag",
      "Text",
      "Text Area",
      "Text Overlay Card Footer Jumbo Button",
      "Theatre Footer variant is used to span edge-to-edge at the bottom of a",
      "container, typically on narrow screens.",
      "Toast",
      "Button label (> ]",
      "Toggle",
      "Tooltip",
      "Video",
      "Android v",
      "ios v",
      "Vue Vv",
      "o",
      "Web Components v Behaviou rs",
      "Patterns v",
      "Subsystems v Text overflow",
      "Support Vv Buttons respect their height. Buttons are able to wrap up to 2",
      "lines of text before truncating their labels.",
      "Really really really long (>)",
      "Jumbo Button label trunc...",
      "Jumbo Buttons are used to emphasise the final step of a",
      "linear flow, typically at the end of a purchase journey",
      "Its core objective is to emphasise a critical action that is to be taken next. Consider only",
      "using the Jumbo Buttons in the final step of a flow, as its visual prominence will be",
      "more useful to convey a critical decision, such as the confirmation of a payment in the",
      "purchase flow.",
      "Contact information Payment method >",
      "Order summary",
      "Being consistent across steps helps create a unified linear flow.",
      "Do not pair Jumbo Buttons with any other secondary",
      "actions",
      "Give the user a clear suggestion on how to move forward by presenting only a single",
      "primary action on each screen.",
      "Delivery details > Delivery details >",
      "Continue shopping",
      "Complete purchase (> ] Complete purchase (> ]",
      "L____________________________________________________________________________. _____________J",
      "(] Present Jumbo Buttons as a stand-alone final action of the screen. (1) Don't pair Jumbo Buttons with secondary actions. Jumbo buttons are only used to",
      "progress linear flows.",
      "Regular Jumbo Button vs. Footer Jumbo Button",
      "Regular variant is suitable for use on larger screens. They are inset and inline like a",
      "typical button. The Footer variant can make the button label and arrow affordance feel",
      "distant when stretched too wide. The Footer variant is better suited to small screens or",
      "containers and usually bookends the screen by filling it from edge to edge.",
      "Payment method >",
      "Comfort configurator",
      ".________________________________________________________________________________ _________________J",
      "(] Use Regular Jumbo Button on larger screens. (] Use Footer Jumbo Button on mobile-only designs.",
      "Use a verb in the label. Be concise.",
      "Buttons perform actions. Use a verb to set the expectation of what action it performs.",
      "Read more about writing for buttons.",
      "Let's complete your purchase",
      "Complete purchase >] i",
      "P P of the planed kitchen",
      "L________________________________________________________________________________ _______________J",
      "(] “Complete purchase” provides clear expectation of this button's action. (1) Avoid use of long labels that read like a sentence. Provide context outside, around",
      "the button instead of inside it.",
      "Internationalisation",
      "RTL languages",
      "Text and Icon will flip its placement position to the opposite side.",
      "(<] ues sled Mails",
      "Keyboard interactions",
      "Key Description",
      "Space / Enter Triggers Button action.",
      "Further reading",
      "Designing forms >",
      "Up next",
      "o",
      "List i",
      "Xx",
      "[*]",
      "[1]",
      "a",
      "b=",
      "7}",
      "1}",
      "[* 9",
      "OD © Inter IKEA Systems B.V 1999-2025"
    ]
  }
}
