{
  "name": "Typography-typeface",
  "category": "Skapa-foundations",
  "source": "Skapa-foundations/Typography-typeface.pdf",
  "extractedAt": "2025-11-01T09:45:33.239Z",
  "metadata": {
    "pages": 0,
    "info": {}
  },
  "content": {
    "rawText": "\n\n-- 1 of 3 --\n\n\n\n-- 2 of 3 --\n\n\n\n-- 3 of 3 --\n\n",
    "lines": [
      "-- 1 of 3 --",
      "-- 2 of 3 --",
      "-- 3 of 3 --"
    ]
  },
  "tokens": {
    "type": "typography",
    "values": [],
    "typography": {
      "fontFamilies": [],
      "fontSizes": [],
      "fontWeights": [],
      "lineHeights": []
    }
  }
}
