{
  "name": "Icons",
  "category": "Skapa-foundations",
  "source": "Skapa-foundations/Icons.pdf",
  "extractedAt": "2025-11-01T09:45:54.446Z",
  "metadata": {
    "pages": 0,
    "info": {}
  },
  "content": {
    "rawText": "\n\n-- 1 of 11 --\n\n\n\n-- 2 of 11 --\n\n\n\n-- 3 of 11 --\n\n\n\n-- 4 of 11 --\n\n\n\n-- 5 of 11 --\n\n\n\n-- 6 of 11 --\n\n\n\n-- 7 of 11 --\n\n\n\n-- 8 of 11 --\n\n\n\n-- 9 of 11 --\n\n\n\n-- 10 of 11 --\n\n\n\n-- 11 of 11 --\n\n",
    "lines": [
      "-- 1 of 11 --",
      "-- 2 of 11 --",
      "-- 3 of 11 --",
      "-- 4 of 11 --",
      "-- 5 of 11 --",
      "-- 6 of 11 --",
      "-- 7 of 11 --",
      "-- 8 of 11 --",
      "-- 9 of 11 --",
      "-- 10 of 11 --",
      "-- 11 of 11 --"
    ]
  },
  "tokens": {
    "type": "iconography",
    "values": []
  }
}
